MANIFEST.in
README.md
setup.py
./variables
status_codes_light/__init__.py
status_codes_light.egg-info/PKG-INFO
status_codes_light.egg-info/SOURCES.txt
status_codes_light.egg-info/dependency_links.txt
status_codes_light.egg-info/top_level.txt
status_codes_light/main/__init__.py
status_codes_light/main/status.py