Metadata-Version: 2.1
Name: status-codes-light
Version: 1.0
Summary: Lightweight library for readable HTTP statuses and helper methods.
Home-page: https://github.com/caisbalderas/simple_status_codes
Author: Carlos Balderas
Author-email: caisbalderas@gmail.com
License: UNKNOWN
Platform: UNKNOWN
Classifier: Operating System :: POSIX :: Linux
Classifier: License :: OSI Approved :: MIT License
Classifier: Programming Language :: Python :: 3.5
Classifier: Programming Language :: Python :: 3.6
Classifier: Programming Language :: Python :: 3.7
